sphinx_link_fixer/__init__.py
sphinx_link_fixer/main.py
sphinx_link_fixer-1.1.3.dist-info/entry_points.txt
sphinx_link_fixer-1.1.3.dist-info/LICENSE
sphinx_link_fixer-1.1.3.dist-info/WHEEL
sphinx_link_fixer-1.1.3.dist-info/METADATA
sphinx_link_fixer-1.1.3.dist-info/RECORD
