Metadata-Version: 2.1
Name: sphinx-link-fixer
Version: 1.1.3
Summary: Convert all relative references to absolute references in .py and .rst files
Author-email: erzo <erzo@posteo.de>
Requires-Python: >=3.6
Classifier: Topic :: Documentation :: Sphinx
Classifier: Environment :: Console
Classifier: License :: OSI Approved :: BSD License
Project-URL: Bug tracker, https://gitlab.com/erzo/sphinx-link-fixer/-/issues
Project-URL: Change log, https://gitlab.com/erzo/sphinx-link-fixer/-/tags
Project-URL: Source code, https://gitlab.com/erzo/sphinx-link-fixer
